{"ip": {"in": {"id": [22861, 22862, 22863, 22864, 22865, 22866, 22867, 22868], "ttl": 64}, "out": {"id": [9063, 9064, 9065, 9066], "ttl": 121}}, "idp_in": "45100088594d4000400663cbc0a81502", "time_end": 1528861046.182922, "p_malware": 7e-06, "expire_type": "i", "entropy": 7.679945, "num_pkts_out": 4, "pr": 6, "time_start": 1528861046.179882, "bytes_in": 640, "num_pkts_in": 8, "bytes_out": 0, "byte_dist_std": 73.521855, "da": "192.168.21.2", "byte_dist_mean": 125.68125, "total_entropy": 4915.164795, "byte_dist": [2, 4, 1, 3, 1, 4, 1, 3, 3, 3, 2, 3, 3, 3, 3, 1, 0, 2, 0, 2, 4, 1, 2, 2, 3, 4, 3, 4, 2, 4, 3, 3, 0, 1, 2, 3, 2, 0, 6, 2, 6, 1, 1, 5, 5, 4, 0, 5, 3, 6, 2, 1, 2, 2, 2, 1, 1, 4, 3, 3, 2, 3, 0, 5, 0, 2, 5, 3, 1, 4, 4, 2, 0, 4, 2, 3, 4, 4, 3, 7, 1, 5, 0, 3, 1, 3, 0, 2, 2, 5, 2, 4, 2, 3, 1, 7, 2, 3, 2, 2, 2, 0, 3, 5, 2, 3, 4, 2, 5, 0, 1, 1, 2, 1, 2, 5, 2, 0, 6, 5, 1, 4, 4, 2, 0, 3, 1, 2, 3, 3, 3, 3, 3, 2, 2, 3, 5, 3, 4, 1, 2, 1, 3, 3, 4, 3, 5, 3, 2, 3, 2, 5, 4, 2, 3, 0, 2, 2, 4, 1, 3, 2, 1, 2, 2, 3, 0, 1, 4, 2, 5, 1, 3, 1, 2, 2, 2, 2, 1, 0, 2, 2, 4, 4, 1, 2, 2, 1, 4, 5, 2, 4, 0, 0, 0, 6, 2, 0, 2, 2, 0, 4, 4, 1, 4, 1, 1, 1, 2, 2, 3, 5, 2, 2, 2, 3, 4, 2, 5, 1, 1, 1, 6, 7, 2, 3, 2, 3, 1, 2, 1, 1, 4, 1, 1, 5, 1, 2, 6, 1, 0, 1, 1, 2, 3, 4, 3, 2, 3, 3, 3, 2, 3, 4, 2, 3], "dp": 22, "idp_len_in": 16, "sp": 63638, "packets": [{"b": 96, "ipt": 0, "dir": "<"}, {"b": 64, "ipt": 0, "dir": "<"}, {"b": 64, "ipt": 0, "dir": "<"}, {"b": 112, "ipt": 0, "dir": "<"}, {"b": 64, "ipt": 0, "dir": "<"}, {"b": 64, "ipt": 0, "dir": "<"}, {"b": 112, "ipt": 0, "dir": "<"}, {"b": 64, "ipt": 0, "dir": "<"}], "sa": "140.112.27.45"}
{"ip": {"in": {"id": [9067], "ttl": 121}, "out": {"id": [4287], "ttl": 64}}, "time_end": 1528861046.224432, "p_malware": 0.000613, "expire_type": "i", "entropy": 6.713156, "num_pkts_out": 1, "pr": 6, "time_start": 1528861046.181045, "bytes_in": 0, "num_pkts_in": 1, "bytes_out": 144, "byte_dist_std": 76.66078, "da": "140.112.27.45", "byte_dist_mean": 124.798611, "idp_len_out": 16, "total_entropy": 966.694427, "byte_dist": [0, 2, 1, 0, 0, 1, 0, 0, 1, 0, 1, 0, 1, 2, 0, 1, 0, 1, 2, 0, 1, 2, 0, 1, 0, 1, 1, 0, 1, 0, 1, 1, 0, 1, 1, 3, 1, 1, 0, 1, 1, 0, 0, 0, 1, 0, 0, 1, 0, 1, 1, 0, 0, 0, 1, 1, 0, 0, 2, 0, 1, 0, 1, 0, 0, 0, 2, 0, 0, 1, 1, 0, 0, 0, 1, 0, 1, 0, 0, 1, 1, 0, 0, 1, 2, 0, 0, 1, 0, 0, 1, 0, 0, 0, 1, 1, 1, 0, 2, 0, 1, 0, 0, 0, 0, 0, 3, 0, 0, 1, 0, 1, 0, 0, 0, 1, 0, 0, 2, 2, 2, 0, 1, 0, 0, 1, 0, 0, 0, 1, 0, 3, 0, 0, 0, 0, 1, 0, 1, 2, 0, 1, 1, 0, 0, 0, 0, 0, 0, 0, 0, 0, 3, 1, 1, 0, 1, 0, 0, 2, 0, 0, 0, 0, 0, 0, 0, 0, 0, 2, 0, 0, 1, 1, 0, 0, 0, 0, 0, 3, 1, 1, 1, 0, 0, 0, 0, 0, 1, 1, 1, 1, 1, 1, 0, 0, 0, 0, 0, 1, 0, 2, 1, 0, 1, 1, 2, 0, 0, 2, 0, 0, 0, 0, 1, 1, 1, 1, 0, 0, 2, 1, 2, 1, 0, 1, 0, 1, 1, 0, 0, 0, 0, 0, 2, 0, 1, 2, 1, 0, 1, 0, 1, 1, 0, 1, 0, 0, 1, 0, 1, 0, 0, 1, 0, 0], "dp": 63637, "sp": 22, "packets": [{"b": 144, "ipt": 0, "dir": ">"}], "idp_out": "451000b810bf40004006ac29c0a81502", "sa": "192.168.21.2"}
{"pr": 6, "time_start": 1528861049.003756, "bytes_out": 0, "sp": 55022, "packets": [], "time_end": 1528861049.00378, "tcp": {"out": {"flags": "S", "first_window_size": 1024}, "first_seq": 3555201947}, "da": "192.168.21.2", "p_malware": 0.000135, "ip": {"in": {"id": [65128], "ttl": 64}, "out": {"id": [26128], "ttl": 239}}, "expire_type": "i", "num_pkts_in": 1, "num_pkts_out": 1, "bytes_in": 0, "sa": "185.156.177.114", "byte_dist": [0, 0, 0, 0, 0, 0, 0, 0, 0, 0, 0, 0, 0, 0, 0, 0, 0, 0, 0, 0, 0, 0, 0, 0, 0, 0, 0, 0, 0, 0, 0, 0, 0, 0, 0, 0, 0, 0, 0, 0, 0, 0, 0, 0, 0, 0, 0, 0, 0, 0, 0, 0, 0, 0, 0, 0, 0, 0, 0, 0, 0, 0, 0, 0, 0, 0, 0, 0, 0, 0, 0, 0, 0, 0, 0, 0, 0, 0, 0, 0, 0, 0, 0, 0, 0, 0, 0, 0, 0, 0, 0, 0, 0, 0, 0, 0, 0, 0, 0, 0, 0, 0, 0, 0, 0, 0, 0, 0, 0, 0, 0, 0, 0, 0, 0, 0, 0, 0, 0, 0, 0, 0, 0, 0, 0, 0, 0, 0, 0, 0, 0, 0, 0, 0, 0, 0, 0, 0, 0, 0, 0, 0, 0, 0, 0, 0, 0, 0, 0, 0, 0, 0, 0, 0, 0, 0, 0, 0, 0, 0, 0, 0, 0, 0, 0, 0, 0, 0, 0, 0, 0, 0, 0, 0, 0, 0, 0, 0, 0, 0, 0, 0, 0, 0, 0, 0, 0, 0, 0, 0, 0, 0, 0, 0, 0, 0, 0, 0, 0, 0, 0, 0, 0, 0, 0, 0, 0, 0, 0, 0, 0, 0, 0, 0, 0, 0, 0, 0, 0, 0, 0, 0, 0, 0, 0, 0, 0, 0, 0, 0, 0, 0, 0, 0, 0, 0, 0, 0, 0, 0, 0, 0, 0, 0, 0, 0, 0, 0, 0, 0, 0, 0, 0, 0, 0, 0], "dp": 25781}
{"ip": {"in": {"id": [31921], "ttl": 59}, "out": {"id": [54742, 54743, 54744, 54745], "ttl": 64}}, "time_end": 1528861051.313736, "p_malware": 0.000161, "expire_type": "i", "entropy": 5.201856, "num_pkts_out": 4, "pr": 6, "time_start": 1528861051.312014, "bytes_in": 0, "num_pkts_in": 1, "bytes_out": 77, "byte_dist_std": 88.545226, "da": "172.217.160.74", "byte_dist_mean": 90.649351, "idp_len_out": 16, "total_entropy": 400.542922, "byte_dist": [16, 0, 0, 4, 0, 0, 1, 1, 1, 0, 0, 1, 0, 0, 0, 0, 0, 0, 0, 0, 0, 1, 0, 1, 0, 1, 1, 0, 0, 0, 0, 1, 0, 0, 1, 0, 0, 0, 0, 2, 2, 1, 0, 0, 0, 0, 0, 1, 0, 1, 1, 1, 0, 0, 0, 0, 0, 0, 0, 1, 0, 1, 0, 0, 0, 0, 0, 0, 0, 0, 0, 0, 0, 1, 0, 0, 0, 0, 1, 0, 0, 0, 0, 0, 0, 0, 0, 0, 0, 0, 0, 0, 2, 0, 0, 0, 0, 0, 0, 0, 0, 0, 0, 0, 1, 0, 0, 0, 0, 1, 0, 0, 0, 1, 1, 0, 0, 1, 0, 0, 0, 0, 0, 0, 0, 0, 0, 0, 0, 0, 0, 1, 0, 0, 0, 1, 0, 0, 0, 0, 1, 0, 1, 0, 0, 0, 0, 0, 0, 1, 0, 0, 1, 0, 0, 0, 0, 0, 0, 0, 0, 0, 0, 0, 0, 0, 0, 0, 0, 0, 0, 0, 0, 1, 1, 0, 1, 1, 0, 0, 0, 0, 0, 0, 0, 1, 0, 0, 0, 1, 0, 0, 0, 0, 0, 0, 0, 0, 1, 0, 0, 0, 1, 0, 0, 0, 0, 0, 0, 0, 0, 1, 0, 0, 0, 0, 0, 0, 1, 1, 0, 0, 0, 0, 0, 2, 0, 0, 0, 0, 0, 0, 1, 1, 0, 0, 0, 1, 0, 0, 0, 0, 1, 0, 0, 1, 0, 0, 0, 0, 0, 0, 2, 0, 1, 0], "dp": 443, "sp": 42556, "packets": [{"b": 46, "ipt": 0, "dir": ">"}, {"b": 31, "ipt": 0, "dir": ">"}], "idp_out": "45000062d5d64000400641f1c0a81502", "sa": "192.168.21.2"}
{"ip": {"in": {"id": [0, 5968, 5969, 5970, 5971, 5972, 5973, 5974, 5975, 5976, 5977, 5978, 5979, 5980, 5981, 5982, 5983, 5984, 5985], "ttl": 64}, "out": {"id": [52054, 52055, 52056, 52057, 52058, 52059, 52060, 52061, 52062, 52063, 52064, 52065, 52066, 52067, 52068, 52069, 52070], "ttl": 39}}, "idp_in": "4500005d17514000400663dac0a81502", "time_end": 1528861062.314964, "tcp": {"out": {"opt_len": 20, "flags": "S", "opts": [{"mss": 1460}, {"sackp": null}, {"ts": {"ecr": 0, "val": 11273144}}, {"noop": null}, {"ws": 7}], "first_window_size": 29200}, "in": {"opt_len": 20, "flags": "SA", "opts": [{"mss": 1460}, {"sackp": null}, {"ts": {"ecr": 11273144, "val": 574296992}}, {"noop": null}, {"ws": 7}], "first_window_size": 28960}, "first_seq": 1963903214}, "p_malware": 0.029554, "expire_type": "i", "entropy": 7.121369, "num_pkts_out": 17, "pr": 6, "time_start": 1528861052.706498, "bytes_in": 2189, "num_pkts_in": 19, "bytes_out": 1391, "byte_dist_std": 46.31872, "da": "192.168.21.2", "byte_dist_mean": 104.584637, "idp_len_out": 16, "total_entropy": 25494.500608, "byte_dist": [148, 19, 5, 7, 8, 11, 6, 14, 8, 5, 11, 4, 12, 4, 2, 9, 5, 7, 7, 10, 12, 11, 7, 7, 4, 9, 4, 9, 5, 5, 7, 9, 12, 6, 5, 6, 8, 10, 9, 9, 11, 5, 5, 9, 78, 133, 38, 6, 17, 58, 78, 14, 19, 40, 39, 6, 24, 21, 8, 6, 13, 5, 10, 11, 39, 18, 4, 8, 8, 6, 5, 8, 8, 5, 10, 9, 5, 9, 3, 9, 6, 9, 7, 12, 7, 15, 3, 7, 9, 7, 6, 11, 4, 6, 8, 5, 3, 113, 27, 129, 29, 99, 22, 22, 103, 34, 12, 11, 26, 87, 55, 72, 52, 10, 49, 143, 41, 30, 6, 10, 7, 11, 8, 7, 7, 10, 5, 6, 11, 3, 6, 14, 4, 10, 6, 10, 7, 5, 9, 6, 9, 10, 4, 6, 5, 9, 8, 9, 8, 8, 12, 7, 7, 8, 5, 5, 7, 8, 7, 9, 9, 5, 7, 12, 10, 10, 6, 8, 7, 4, 11, 8, 4, 7, 5, 11, 6, 10, 11, 7, 6, 5, 8, 4, 8, 7, 4, 8, 11, 5, 9, 9, 10, 12, 10, 3, 4, 7, 7, 4, 7, 4, 4, 7, 9, 2, 7, 4, 10, 8, 6, 5, 8, 8, 10, 8, 15, 3, 8, 4, 4, 8, 10, 8, 5, 12, 5, 9, 4, 8, 10, 6, 5, 14, 5, 7, 12, 7, 7, 7, 10, 13, 7, 4, 10, 3, 5, 6, 8, 2, 10, 9, 8, 6, 11, 5], "dp": 22, "idp_len_in": 16, "sp": 27982, "packets": [{"b": 15, "ipt": 315, "dir": ">"}, {"b": 41, "ipt": 5, "dir": "<"}, {"b": 976, "ipt": 314, "dir": "<"}, {"b": 648, "ipt": 0, "dir": ">"}, {"b": 272, "ipt": 358, "dir": ">"}, {"b": 848, "ipt": 2, "dir": "<"}, {"b": 16, "ipt": 318, "dir": ">"}, {"b": 52, "ipt": 359, "dir": ">"}, {"b": 52, "ipt": 0, "dir": "<"}, {"b": 68, "ipt": 315, "dir": ">"}, {"b": 68, "ipt": 2, "dir": "<"}, {"b": 100, "ipt": 315, "dir": ">"}, {"b": 68, "ipt": 2183, "dir": "<"}, {"b": 84, "ipt": 315, "dir": ">"}, {"b": 68, "ipt": 2123, "dir": "<"}, {"b": 84, "ipt": 314, "dir": ">"}, {"b": 68, "ipt": 1732, "dir": "<"}, {"b": 52, "ipt": 315, "dir": ">"}], "idp_out": "45280043cb5840002706c8c43db1ac14", "sa": "61.177.172.20"}
{"pr": 6, "time_start": 1528861061.850174, "bytes_out": 0, "sp": 55036, "packets": [], "time_end": 1528861061.850198, "tcp": {"out": {"flags": "S", "first_window_size": 1024}, "first_seq": 2466096784}, "da": "192.168.21.2", "p_malware": 0.00032, "ip": {"in": {"id": [60449], "ttl": 64}, "out": {"id": [43471], "ttl": 230}}, "expire_type": "i", "num_pkts_in": 1, "num_pkts_out": 1, "bytes_in": 0, "sa": "80.82.70.187", "byte_dist": [0, 0, 0, 0, 0, 0, 0, 0, 0, 0, 0, 0, 0, 0, 0, 0, 0, 0, 0, 0, 0, 0, 0, 0, 0, 0, 0, 0, 0, 0, 0, 0, 0, 0, 0, 0, 0, 0, 0, 0, 0, 0, 0, 0, 0, 0, 0, 0, 0, 0, 0, 0, 0, 0, 0, 0, 0, 0, 0, 0, 0, 0, 0, 0, 0, 0, 0, 0, 0, 0, 0, 0, 0, 0, 0, 0, 0, 0, 0, 0, 0, 0, 0, 0, 0, 0, 0, 0, 0, 0, 0, 0, 0, 0, 0, 0, 0, 0, 0, 0, 0, 0, 0, 0, 0, 0, 0, 0, 0, 0, 0, 0, 0, 0, 0, 0, 0, 0, 0, 0, 0, 0, 0, 0, 0, 0, 0, 0, 0, 0, 0, 0, 0, 0, 0, 0, 0, 0, 0, 0, 0, 0, 0, 0, 0, 0, 0, 0, 0, 0, 0, 0, 0, 0, 0, 0, 0, 0, 0, 0, 0, 0, 0, 0, 0, 0, 0, 0, 0, 0, 0, 0, 0, 0, 0, 0, 0, 0, 0, 0, 0, 0, 0, 0, 0, 0, 0, 0, 0, 0, 0, 0, 0, 0, 0, 0, 0, 0, 0, 0, 0, 0, 0, 0, 0, 0, 0, 0, 0, 0, 0, 0, 0, 0, 0, 0, 0, 0, 0, 0, 0, 0, 0, 0, 0, 0, 0, 0, 0, 0, 0, 0, 0, 0, 0, 0, 0, 0, 0, 0, 0, 0, 0, 0, 0, 0, 0, 0, 0, 0, 0, 0, 0, 0, 0, 0], "dp": 7777}
{"pr": 6, "time_start": 1528861065.471705, "bytes_out": 0, "sp": 55022, "packets": [], "time_end": 1528861065.471729, "tcp": {"out": {"flags": "S", "first_window_size": 1024}, "first_seq": 1218044302}, "da": "192.168.21.2", "p_malware": 0.000147, "ip": {"in": {"id": [65341], "ttl": 64}, "out": {"id": [44406], "ttl": 239}}, "expire_type": "i", "num_pkts_in": 1, "num_pkts_out": 1, "bytes_in": 0, "sa": "185.156.177.114", "byte_dist": [0, 0, 0, 0, 0, 0, 0, 0, 0, 0, 0, 0, 0, 0, 0, 0, 0, 0, 0, 0, 0, 0, 0, 0, 0, 0, 0, 0, 0, 0, 0, 0, 0, 0, 0, 0, 0, 0, 0, 0, 0, 0, 0, 0, 0, 0, 0, 0, 0, 0, 0, 0, 0, 0, 0, 0, 0, 0, 0, 0, 0, 0, 0, 0, 0, 0, 0, 0, 0, 0, 0, 0, 0, 0, 0, 0, 0, 0, 0, 0, 0, 0, 0, 0, 0, 0, 0, 0, 0, 0, 0, 0, 0, 0, 0, 0, 0, 0, 0, 0, 0, 0, 0, 0, 0, 0, 0, 0, 0, 0, 0, 0, 0, 0, 0, 0, 0, 0, 0, 0, 0, 0, 0, 0, 0, 0, 0, 0, 0, 0, 0, 0, 0, 0, 0, 0, 0, 0, 0, 0, 0, 0, 0, 0, 0, 0, 0, 0, 0, 0, 0, 0, 0, 0, 0, 0, 0, 0, 0, 0, 0, 0, 0, 0, 0, 0, 0, 0, 0, 0, 0, 0, 0, 0, 0, 0, 0, 0, 0, 0, 0, 0, 0, 0, 0, 0, 0, 0, 0, 0, 0, 0, 0, 0, 0, 0, 0, 0, 0, 0, 0, 0, 0, 0, 0, 0, 0, 0, 0, 0, 0, 0, 0, 0, 0, 0, 0, 0, 0, 0, 0, 0, 0, 0, 0, 0, 0, 0, 0, 0, 0, 0, 0, 0, 0, 0, 0, 0, 0, 0, 0, 0, 0, 0, 0, 0, 0, 0, 0, 0, 0, 0, 0, 0, 0, 0], "dp": 24006}
